sqlite_dump/__init__.py
sqlite_dump-0.1.1.dist-info/LICENSE
sqlite_dump-0.1.1.dist-info/METADATA
sqlite_dump-0.1.1.dist-info/WHEEL
sqlite_dump-0.1.1.dist-info/top_level.txt
sqlite_dump-0.1.1.dist-info/RECORD
