Metadata-Version: 2.1
Name: sqlite-dump
Version: 0.1.1
Summary: An improved version of .iterdump() for sqlite3
Home-page: https://github.com/simonw/sqlite-dump
Author: Simon Willison
License: Apache License, Version 2.0
Project-URL: Issues, https://github.com/simonw/sqlite-dump/issues
Project-URL: CI, https://github.com/simonw/sqlite-dump/actions
Project-URL: Changelog, https://github.com/simonw/sqlite-dump/releases
Platform: UNKNOWN
Provides-Extra: test
Requires-Dist: pytest ; extra == 'test'
Requires-Dist: sqlite-utils ; extra == 'test'
